<?xml version="1.0" encoding="UTF-8"?>

<newsitem date="1997-04-03" id="root" itemid="82256" xml:lang="da">
<title></title>
<headline> S-E-Banken udpeger obligationschef i Danmark. </headline>
<byline></byline>
<dateline></dateline>
<text>
<p> STOCKHOLM, 3 april (Reuter) - Peter Høltermand er udpeget til obligationschef for S-E-Bankens obligationshandel i Danmark, oplyser den svenske bank torsdag. </p>
<p> Obligationsafdelingen skal omfatte 16 personer, og handlen forventes at begynde til sommer. </p>
<p> Peter Høltermand har tidligere været obligationschef hos Alfred Berg. </p>
<p> - (/Reuter) +46 87 00 1010. </p>
<p> (c) Reuters Limited 1997. </p></text>
<copyright>(c) 1997 Reuters Limited</copyright>
<metadata>
<codes class="bip:countries:1.0">
<code code="DEN">
<editdetail action="confirmed" attribution="Reuters BIP Coding Group" date="1997-04-03"></editdetail></code>
<code code="EURZ">
<editdetail action="confirmed" attribution="Reuters BIP Coding Group" date="1997-04-03"></editdetail></code>
<code code="SCANDZ">
<editdetail action="confirmed" attribution="Reuters BIP Coding Group" date="1997-04-03"></editdetail></code>
<code code="SWED">
<editdetail action="confirmed" attribution="Reuters BIP Coding Group" date="1997-04-03"></editdetail></code>
<code code="WEURZ">
<editdetail action="confirmed" attribution="Reuters BIP Coding Group" date="1997-04-03"></editdetail></code></codes>
<codes class="bip:topics:1.0">
<code code="SEB">
<editdetail action="confirmed" attribution="Reuters BIP Coding Group" date="1997-04-03"></editdetail></code>
<code code="I814">
<editdetail action="confirmed" attribution="Reuters BIP Coding Group" date="1997-04-03"></editdetail></code>
<code code="I81402">
<editdetail action="confirmed" attribution="Reuters BIP Coding Group" date="1997-04-03"></editdetail></code>
<code code="IBNK">
<editdetail action="confirmed" attribution="Reuters BIP Coding Group" date="1997-04-03"></editdetail></code>
<code code="C41">
<editdetail action="confirmed" attribution="Reuters BIP Coding Group" date="1997-04-03"></editdetail></code>
<code code="C411">
<editdetail action="confirmed" attribution="Reuters BIP Coding Group" date="1997-04-03"></editdetail></code>
<code code="CCAT">
<editdetail action="confirmed" attribution="Reuters BIP Coding Group" date="1997-04-03"></editdetail></code></codes>
<dc element="dc.publisher" value="Reuters Holdings Plc"></dc>
<dc element="dc.datepublished" value="1997-04-03"></dc>
<dc element="dc.source" value="Reuters - Nyheder på dansk"></dc>
<dc element="dc.creator.location" value=""></dc>
<dc element="dc.creator.location.country.name" value=""></dc></metadata></newsitem>