<?xml version="1.0" encoding="UTF-8"?>

<newsitem date="1997-04-22" id="root" itemid="82887" xml:lang="da">
<title></title>
<headline> SAS sænker priser på forretningsrejser - SAS. </headline>
<byline></byline>
<dateline></dateline>
<text>
<p> STOCKHOLM, 22 april (Reuter) - SAS sænker priserne på forretningsrejser mellem Skandinavien og Europa. Samtidig indfører koncernen en ny billettype, EuroSaver, som stort giver de samme fordele som en billet til fuld pris, men til en betydelig lavere pris. Det oplyser flyselskabet tirsdag i en pressemeddelelse. </p>
<p> (c) Reuters Limited 1997. </p></text>
<copyright>(c) 1997 Reuters Limited</copyright>
<metadata>
<codes class="bip:countries:1.0">
<code code="DEN">
<editdetail action="confirmed" attribution="Reuters BIP Coding Group" date="1997-04-22"></editdetail></code>
<code code="EUR">
<editdetail action="confirmed" attribution="Reuters BIP Coding Group" date="1997-04-22"></editdetail></code>
<code code="EURZ">
<editdetail action="confirmed" attribution="Reuters BIP Coding Group" date="1997-04-22"></editdetail></code>
<code code="SCAND">
<editdetail action="confirmed" attribution="Reuters BIP Coding Group" date="1997-04-22"></editdetail></code>
<code code="SCANDZ">
<editdetail action="confirmed" attribution="Reuters BIP Coding Group" date="1997-04-22"></editdetail></code>
<code code="WEURZ">
<editdetail action="confirmed" attribution="Reuters BIP Coding Group" date="1997-04-22"></editdetail></code></codes>
<codes class="bip:topics:1.0">
<code code="SAS">
<editdetail action="confirmed" attribution="Reuters BIP Coding Group" date="1997-04-22"></editdetail></code>
<code code="I75">
<editdetail action="confirmed" attribution="Reuters BIP Coding Group" date="1997-04-22"></editdetail></code>
<code code="C22">
<editdetail action="confirmed" attribution="Reuters BIP Coding Group" date="1997-04-22"></editdetail></code>
<code code="C31">
<editdetail action="confirmed" attribution="Reuters BIP Coding Group" date="1997-04-22"></editdetail></code>
<code code="CCAT">
<editdetail action="confirmed" attribution="Reuters BIP Coding Group" date="1997-04-22"></editdetail></code></codes>
<dc element="dc.publisher" value="Reuters Holdings Plc"></dc>
<dc element="dc.datepublished" value="1997-04-22"></dc>
<dc element="dc.source" value="Reuters - Nyheder på dansk"></dc>
<dc element="dc.creator.location" value=""></dc>
<dc element="dc.creator.location.country.name" value=""></dc></metadata></newsitem>