<?xml version="1.0" encoding="UTF-8"?>

<newsitem date="1997-07-18" id="root" itemid="85838" xml:lang="da">
<title></title>
<headline> Malaysisk Danyard-køber afslutter nyt køb - PSCI. </headline>
<byline></byline>
<dateline></dateline>
<text>
<p> KØBENHAVN, 18 juli (Reuter) - Malaysiske Penang Shipbuilding Construction Industries har afsluttet købet af en ejendom i den nordlige del af Penang-staten, meddeler selskabet. Ejendommen købes for 9,7 mio. malaysiske ringgit (ca. 25 mio. kr.). </p>
<p> Efter udsendelsen af meddelelsen blev handlen med PSCI-aktien genoptaget på børsen i Kuala Lumpur. Aktien har været suspenderet fra handel siden den 3. juli på grund af købet. </p>
<p> PSCI har indgået aftale om at overtage knap halvdelen af J. Lauritzen Holdings Danyard-værft. Den aftalte pris er 100 mio. USD. </p>
<p> Den malaysiske ringgit nåede i dag fredag det svageste niveau over for den amerikanske dollar i tre år og ventes ifølge malaysiske handlere at blive svækket yderligere. </p>
<p> - Stig Ørskov Pedersen (+45) 33 96 96 59. </p>
<p> (c) Reuters Limited 1997. </p></text>
<copyright>(c) 1997 Reuters Limited</copyright>
<metadata>
<codes class="bip:countries:1.0">
<code code="ASIAZ">
<editdetail action="confirmed" attribution="Reuters BIP Coding Group" date="1997-07-18"></editdetail></code>
<code code="DEN">
<editdetail action="confirmed" attribution="Reuters BIP Coding Group" date="1997-07-18"></editdetail></code>
<code code="DEVGCOZ">
<editdetail action="confirmed" attribution="Reuters BIP Coding Group" date="1997-07-18"></editdetail></code>
<code code="EURZ">
<editdetail action="confirmed" attribution="Reuters BIP Coding Group" date="1997-07-18"></editdetail></code>
<code code="MALAY">
<editdetail action="confirmed" attribution="Reuters BIP Coding Group" date="1997-07-18"></editdetail></code>
<code code="SCANDZ">
<editdetail action="confirmed" attribution="Reuters BIP Coding Group" date="1997-07-18"></editdetail></code>
<code code="SEASIAZ">
<editdetail action="confirmed" attribution="Reuters BIP Coding Group" date="1997-07-18"></editdetail></code>
<code code="WEURZ">
<editdetail action="confirmed" attribution="Reuters BIP Coding Group" date="1997-07-18"></editdetail></code></codes>
<codes class="bip:topics:1.0">
<code code="JLAUR">
<editdetail action="confirmed" attribution="Reuters BIP Coding Group" date="1997-07-18"></editdetail></code>
<code code="SDPMAL">
<editdetail action="confirmed" attribution="Reuters BIP Coding Group" date="1997-07-18"></editdetail></code>
<code code="I74">
<editdetail action="confirmed" attribution="Reuters BIP Coding Group" date="1997-07-18"></editdetail></code>
<code code="ITSP">
<editdetail action="confirmed" attribution="Reuters BIP Coding Group" date="1997-07-18"></editdetail></code>
<code code="C31">
<editdetail action="confirmed" attribution="Reuters BIP Coding Group" date="1997-07-18"></editdetail></code>
<code code="CCAT">
<editdetail action="confirmed" attribution="Reuters BIP Coding Group" date="1997-07-18"></editdetail></code>
<code code="M11">
<editdetail action="confirmed" attribution="Reuters BIP Coding Group" date="1997-07-18"></editdetail></code>
<code code="MCAT">
<editdetail action="confirmed" attribution="Reuters BIP Coding Group" date="1997-07-18"></editdetail></code></codes>
<dc element="dc.publisher" value="Reuters Holdings Plc"></dc>
<dc element="dc.datepublished" value="1997-07-18"></dc>
<dc element="dc.source" value="Reuters - Nyheder på dansk"></dc>
<dc element="dc.creator.location" value=""></dc>
<dc element="dc.creator.location.country.name" value=""></dc></metadata></newsitem>