<?xml version="1.0" encoding="UTF-8"?>

<newsitem date="1997-08-13" id="root" itemid="86628" xml:lang="da">
<title></title>
<headline> Skjern Bank øger forventninger til hele 1997. </headline>
<byline></byline>
<dateline></dateline>
<text>
<p> KØBENHAVN, 13 august (Reuter) - Skjern Bank opjusterer i forbindelse med offentliggørelsen af halvårsregnskabet sine forventninger til hele 1997, fremgår det. </p>
<p> - Med udgangspunkt i udsigterne til et uændret renteniveau i resten af 1997, opjusterer banken sine forventninger til 1997-resultat til at ligge på niveau med 1996, det vil sige et resultat før skat på ca. 26 mio. kr., skriver ledelsen i halvårsregnskabet, der viste et resultat før skat på 18,3 mio. kr. mod 12,8 mio. kr. i den tilsvarende periode sidste år. </p>
<p> Ledelsen i banken har tidligere givet udtryk for en forventning om et lidt lavere resultat i 1997 end i 1996. </p>
<p> (c) Reuters Limited 1997. </p></text>
<copyright>(c) 1997 Reuters Limited</copyright>
<metadata>
<codes class="bip:countries:1.0">
<code code="DEN">
<editdetail action="confirmed" attribution="Reuters BIP Coding Group" date="1997-08-13"></editdetail></code>
<code code="EURZ">
<editdetail action="confirmed" attribution="Reuters BIP Coding Group" date="1997-08-13"></editdetail></code>
<code code="SCANDZ">
<editdetail action="confirmed" attribution="Reuters BIP Coding Group" date="1997-08-13"></editdetail></code>
<code code="WEURZ">
<editdetail action="confirmed" attribution="Reuters BIP Coding Group" date="1997-08-13"></editdetail></code></codes>
<codes class="bip:topics:1.0">
<code code="SKBK">
<editdetail action="confirmed" attribution="Reuters BIP Coding Group" date="1997-08-13"></editdetail></code>
<code code="I814">
<editdetail action="confirmed" attribution="Reuters BIP Coding Group" date="1997-08-13"></editdetail></code>
<code code="I81402">
<editdetail action="confirmed" attribution="Reuters BIP Coding Group" date="1997-08-13"></editdetail></code>
<code code="IBNK">
<editdetail action="confirmed" attribution="Reuters BIP Coding Group" date="1997-08-13"></editdetail></code>
<code code="C15">
<editdetail action="confirmed" attribution="Reuters BIP Coding Group" date="1997-08-13"></editdetail></code>
<code code="C152">
<editdetail action="confirmed" attribution="Reuters BIP Coding Group" date="1997-08-13"></editdetail></code>
<code code="CCAT">
<editdetail action="confirmed" attribution="Reuters BIP Coding Group" date="1997-08-13"></editdetail></code></codes>
<dc element="dc.publisher" value="Reuters Holdings Plc"></dc>
<dc element="dc.datepublished" value="1997-08-13"></dc>
<dc element="dc.source" value="Reuters - Nyheder på dansk"></dc>
<dc element="dc.creator.location" value=""></dc>
<dc element="dc.creator.location.country.name" value=""></dc></metadata></newsitem>