<?xml version="1.0" encoding="UTF-8"?>

<newsitem date="1997-07-29" id="root" itemid="86085" xml:lang="da">
<title></title>
<headline> DDB, FLS, Novo, Tele DK og SAS trækker KFX ned. </headline>
<byline></byline>
<dateline></dateline>
<text>
<p>     KØBENHAVN, 29 juli (Reuter) - Det danske aktiemarked </p>
<p> tirsdag kl. 12.15:       +/- </p>
<p>     * KFX-indekset............. 189,21     -1,39 </p>
<p>     * August-future på KFX..... 189,70     +0,72 </p>
<p>     * Omsætning i KFX-papirer.. 132 mio. kr. </p>
<p>     * Kursfald i Den Danske Bank, FLS, Novo Nordisk og </p>
<p> Tele Danmark trækker KFX-indeks i nedadgående retning. </p>
<p>     * SAS og Falck falder tilbage efter den seneste tids </p>
<p> kursstigninger. </p>
<p>     * Lindab falder knap seks. pct., til kurs 95 selv om </p>
<p> Nomura har anbefalet aktien op til kurs 135 SEK. </p>
<p> (c) Reuters Limited 1997. </p></text>
<copyright>(c) 1997 Reuters Limited</copyright>
<metadata>
<codes class="bip:countries:1.0">
<code code="DEN">
<editdetail action="confirmed" attribution="Reuters BIP Coding Group" date="1997-07-29"></editdetail></code>
<code code="EURZ">
<editdetail action="confirmed" attribution="Reuters BIP Coding Group" date="1997-07-29"></editdetail></code>
<code code="SCANDZ">
<editdetail action="confirmed" attribution="Reuters BIP Coding Group" date="1997-07-29"></editdetail></code>
<code code="WEURZ">
<editdetail action="confirmed" attribution="Reuters BIP Coding Group" date="1997-07-29"></editdetail></code></codes>
<codes class="bip:topics:1.0">
<code code="M11">
<editdetail action="confirmed" attribution="Reuters BIP Coding Group" date="1997-07-29"></editdetail></code>
<code code="MCAT">
<editdetail action="confirmed" attribution="Reuters BIP Coding Group" date="1997-07-29"></editdetail></code></codes>
<dc element="dc.publisher" value="Reuters Holdings Plc"></dc>
<dc element="dc.datepublished" value="1997-07-29"></dc>
<dc element="dc.source" value="Reuters - Nyheder på dansk"></dc>
<dc element="dc.creator.location" value=""></dc>
<dc element="dc.creator.location.country.name" value=""></dc></metadata></newsitem>