<?xml version="1.0" encoding="UTF-8"?>

<newsitem date="1996-10-18" id="root" itemid="76954" xml:lang="da">
<title></title>
<headline> APM FORDOBLER OLIEKAPACITET I QATAR - BN. </headline>
<byline></byline>
<dateline></dateline>
<text>
<p> KØBENHAVN, 18 oktober (Reuter) - A. P. Møller (APM) øger sine olie-investeringer i Qatar, så en del af anlægget bygges til en produktionskapacitet på 150.000 tønder om dagen. Det er dobbelt så meget, som A. P. Møller tidligere har sat i udsigt som spidsproduktion fire-fem år frem i tiden. Det skriver Børsens Nyhedsmagasin (BN). </p>
<p> - Betyder det, at der er dobbelt så meget olie i Qatar-feltet, som A.P. Møller hidtil har oplyst, spørger Børsens Nyhedsmagasin. </p>
<p> En anden mulighed kunne imidlertid være, at APM vil pumpe olien i sit mest fremskredne udenlandske olieeventyr hurtigere op end hidtil antaget. Begge dele vil have betydning for APM Gruppens indtjening, understreger Børsens Nyhedsmagasin. </p>
<p> Det danske konglomerat forklarer selv den voldsomme udvidelse af produktionskapaciteten i Qatar med rent købmandsskab. </p>
<p> - Visse dele af produktionsanlægget, som vil være forholdsvis dyre senere at udvide, bygges mod en meget beskeden ekstraomkostning med en højere kapacitet, oplyser A. P. Møller til Børsens Nyhedsmagasin. </p>
<p> APM tilføjer, at der på nuværende tidspunkt ikke er grundlag for at investere i produktionsbrønde til mere end ca. 75.000 tønder om dagen. </p>
<p> - Med andre ord holdes muligheden altså åben for at kunne udvide produktionen kraftigt. Men her og nu er der ikke udsigt til det, skriver Børsens Nyhedsmagasin. </p>
<p> Det er APM Gruppens erklærede mål, at olieproduktionen i udlandet skal overstige olieproduktionen i Danmark, der i DUC-regi i 1995 var på 185.000 tønder om dagen. APM satser ud over Qatar på olieefterforskning og - produktion i Kina, Thailand, Indonesien, Skotland, Algeriet, Tyskland og Færøerne. (/slj). </p>
<p> (c) Reuters Limited 1996. </p></text>
<copyright>(c) 1996 Reuters Limited</copyright>
<metadata>
<codes class="bip:countries:1.0">
<code code="ASIAZ">
<editdetail action="confirmed" attribution="Reuters BIP Coding Group" date="1996-10-18"></editdetail></code>
<code code="DEN">
<editdetail action="confirmed" attribution="Reuters BIP Coding Group" date="1996-10-18"></editdetail></code>
<code code="DEVGCOZ">
<editdetail action="confirmed" attribution="Reuters BIP Coding Group" date="1996-10-18"></editdetail></code>
<code code="EURZ">
<editdetail action="confirmed" attribution="Reuters BIP Coding Group" date="1996-10-18"></editdetail></code>
<code code="GULFSTZ">
<editdetail action="confirmed" attribution="Reuters BIP Coding Group" date="1996-10-18"></editdetail></code>
<code code="MEASTZ">
<editdetail action="confirmed" attribution="Reuters BIP Coding Group" date="1996-10-18"></editdetail></code>
<code code="QATAR">
<editdetail action="confirmed" attribution="Reuters BIP Coding Group" date="1996-10-18"></editdetail></code>
<code code="SCANDZ">
<editdetail action="confirmed" attribution="Reuters BIP Coding Group" date="1996-10-18"></editdetail></code>
<code code="WASIAZ">
<editdetail action="confirmed" attribution="Reuters BIP Coding Group" date="1996-10-18"></editdetail></code>
<code code="WEURZ">
<editdetail action="confirmed" attribution="Reuters BIP Coding Group" date="1996-10-18"></editdetail></code></codes>
<codes class="bip:topics:1.0">
<code code="MOELR">
<editdetail action="confirmed" attribution="Reuters BIP Coding Group" date="1996-10-18"></editdetail></code>
<code code="I1">
<editdetail action="confirmed" attribution="Reuters BIP Coding Group" date="1996-10-18"></editdetail></code>
<code code="I13">
<editdetail action="confirmed" attribution="Reuters BIP Coding Group" date="1996-10-18"></editdetail></code>
<code code="I1300013">
<editdetail action="confirmed" attribution="Reuters BIP Coding Group" date="1996-10-18"></editdetail></code>
<code code="I74">
<editdetail action="confirmed" attribution="Reuters BIP Coding Group" date="1996-10-18"></editdetail></code>
<code code="ITSP">
<editdetail action="confirmed" attribution="Reuters BIP Coding Group" date="1996-10-18"></editdetail></code>
<code code="C24">
<editdetail action="confirmed" attribution="Reuters BIP Coding Group" date="1996-10-18"></editdetail></code>
<code code="CCAT">
<editdetail action="confirmed" attribution="Reuters BIP Coding Group" date="1996-10-18"></editdetail></code></codes>
<dc element="dc.publisher" value="Reuters Holdings Plc"></dc>
<dc element="dc.datepublished" value="1996-10-18"></dc>
<dc element="dc.source" value="Reuters - Nyheder på dansk"></dc>
<dc element="dc.creator.location" value=""></dc>
<dc element="dc.creator.location.country.name" value=""></dc></metadata></newsitem>