<?xml version="1.0" encoding="UTF-8"?>

<newsitem date="1996-11-08" id="root" itemid="77407" xml:lang="da">
<title></title>
<headline> HØJERE RENTESPÆND KAN TILTRÆKKE UDLÆNDINGE. </headline>
<byline></byline>
<dateline></dateline>
<text>
<p> KØBENHAVN, 8 november (Reuter) - Det 10-årige dansk-tyske rentespænd blev torsdag udvidet til 94 bp og ligger fredag morgen i niveauet 95-96 bp. Det bør ifølge en markedsdeltager tiltrække flere udenlandske købere til det danske obligationsmarked. </p>
<p> - Rentespændet bør holde 95 bp, men det afhænger af, hvad de store London-huse foretager sig, siger samme markedsdeltager. </p>
<p> Statens 8 pct. 2006 ses åbne omkring 107,80 mod 107,55 sent torsdag. Det stærkere marked læner sig op af kraftigt stigende amerikanske obligationsmarked. </p>
<p> (c) Reuters Limited 1996. </p></text>
<copyright>(c) 1996 Reuters Limited</copyright>
<metadata>
<codes class="bip:countries:1.0">
<code code="DEN">
<editdetail action="confirmed" attribution="Reuters BIP Coding Group" date="1996-11-08"></editdetail></code>
<code code="EURZ">
<editdetail action="confirmed" attribution="Reuters BIP Coding Group" date="1996-11-08"></editdetail></code>
<code code="SCANDZ">
<editdetail action="confirmed" attribution="Reuters BIP Coding Group" date="1996-11-08"></editdetail></code>
<code code="WEURZ">
<editdetail action="confirmed" attribution="Reuters BIP Coding Group" date="1996-11-08"></editdetail></code></codes>
<codes class="bip:topics:1.0">
<code code="M12">
<editdetail action="confirmed" attribution="Reuters BIP Coding Group" date="1996-11-08"></editdetail></code>
<code code="MCAT">
<editdetail action="confirmed" attribution="Reuters BIP Coding Group" date="1996-11-08"></editdetail></code></codes>
<dc element="dc.publisher" value="Reuters Holdings Plc"></dc>
<dc element="dc.datepublished" value="1996-11-08"></dc>
<dc element="dc.source" value="Reuters - Nyheder på dansk"></dc>
<dc element="dc.creator.location" value=""></dc>
<dc element="dc.creator.location.country.name" value=""></dc></metadata></newsitem>