<?xml version="1.0" encoding="UTF-8"?>

<newsitem date="1996-12-16" id="root" itemid="78302" xml:lang="da">
<title></title>
<headline> Valuta - ØMU-stabilitetspagt svækker DEM. </headline>
<byline></byline>
<dateline></dateline>
<text>
<p>     KØBENHAVN, 16 december (Reuter) - EU-topmødet i </p>
<p> weekenden bragte en foreløbig afslutning på diskussionen </p>
<p> om en post-ØMU stabilitetspagt, og det svækkede den tyske </p>
<p> D-mark i mandagens europæiske valutahandel. </p>
<p>     D-marken er faldet mere end en pfennig over for </p>
<p> dollaren til 1,5555. </p>
<p>     - Markedets første reaktion til stabilitetspagten har </p>
<p> været negativ for D-marken, hvilket er helt naturligt, </p>
<p> siger Tony Norfield fra ABN AMRO. </p>
<p>     D-marken er faldet til 983,85 DFEM/ITL fra 984,50 </p>
<p> fredag og svækket til 3,8250 DEM/DKK mod den danske krone. </p>
<p>  @ </p>
<p>     Ifølge den vedtagne stabilitetspagt skal lande hvis </p>
<p> årlige budgetunderskud overstiger tre pct. af BNP idømmes </p>
<p> en bøde på 0,2 pct. af BNP eller mere. Hvis et lands </p>
<p> økonomi sammentrækker sig med mellem 0,75 pct. og to pct., </p>
<p> skal regeringerne mødes for at diskutere omstændighederne </p>
<p> og en eventuel bøde, mens hvis sammentrækningen er på </p>
<p> mere end to pct., undgår det pågældende land automatisk </p>
<p> bøden. </p>
<p>    @ </p>
<p>     Tony Norfield mener, at pagten øger sandsynligheden </p>
<p> for at Spanien og Italien vil være med fra starten af </p>
<p> ØMUðen i 1999, men at den skattepolitiske &quot;spændetrøje&quot; </p>
<p> som pagten repræsenterer for de deltagende lande, er </p>
<p> negativ for den nye europæiske valuta i forholdet til </p>
<p> dollaren. </p>
<p>     På kort sigt ser tekniske analytikere 1,5580 USD/DEM </p>
<p> som modstandspunkt, hvorefter 1,5735 er næste mål. </p>
<p>     Det tyske Ifo-institut offentliggjorde i dag sit </p>
<p> indeks over forventningerne til udviklingen i den tyske </p>
<p> økonomi. </p>
<p>     Analytikere havde ventet en stigning fra oktobers </p>
<p> indeksværdi på 97,3, men i stedet faldt indekset til 96,9. </p>
<p>        DEM/DKK  USD/DKK FRF/DKK USD/JPY USD/DEM </p>
<p> Mandag    11.00  3,8250   5,9475  1,1340  113,75  1,5555 </p>
<p> Fredag    15.17  3,8295   5,9035  1,1335  113,45  1,5415 </p>
<p> (/clm). </p>
<p> (c) Reuters Limited 1996. </p></text>
<copyright>(c) 1996 Reuters Limited</copyright>
<metadata>
<codes class="bip:countries:1.0">
<code code="DEN">
<editdetail action="confirmed" attribution="Reuters BIP Coding Group" date="1996-12-16"></editdetail></code>
<code code="EURZ">
<editdetail action="confirmed" attribution="Reuters BIP Coding Group" date="1996-12-16"></editdetail></code>
<code code="SCANDZ">
<editdetail action="confirmed" attribution="Reuters BIP Coding Group" date="1996-12-16"></editdetail></code>
<code code="WEURZ">
<editdetail action="confirmed" attribution="Reuters BIP Coding Group" date="1996-12-16"></editdetail></code></codes>
<codes class="bip:topics:1.0">
<code code="M13">
<editdetail action="confirmed" attribution="Reuters BIP Coding Group" date="1996-12-16"></editdetail></code>
<code code="M132">
<editdetail action="confirmed" attribution="Reuters BIP Coding Group" date="1996-12-16"></editdetail></code>
<code code="MCAT">
<editdetail action="confirmed" attribution="Reuters BIP Coding Group" date="1996-12-16"></editdetail></code></codes>
<dc element="dc.publisher" value="Reuters Holdings Plc"></dc>
<dc element="dc.datepublished" value="1996-12-16"></dc>
<dc element="dc.source" value="Reuters - Nyheder på dansk"></dc>
<dc element="dc.creator.location" value=""></dc>
<dc element="dc.creator.location.country.name" value=""></dc></metadata></newsitem>