<?xml version="1.0" encoding="UTF-8"?>

<newsitem date="1997-01-03" id="root" itemid="78679" xml:lang="da">
<title></title>
<headline> UDSIGT TIL STILLE AKTIEMARKED, SES HOLDE NIVEAU. </headline>
<byline></byline>
<dateline></dateline>
<text>
<p> KØBENHAVN, 3 januar (Reuter) - Aktiemarkedet ventes at gå en stille og rolig fredag i møde, hvor markedet kan slutter dagen omkring niveauet, vurderer en handler. </p>
<p> - NAPM-tallet gav lidt rystelser i USA, hvor markedet åbnede temmelig negativt. Stemningen ændrede sig dog lidt og USA lukkede stort set på niveauet. Tonen på det hjemlige marked er stadigvæk positiv, men det mulige salg af medarbejderaktier i Novo kan presse KFX-indekset i modsat retning, siger handleren. </p>
<p> KFX-indekset sluttede årets første handelsdag 1,45 point lavere i 134,68. </p>
<p> (c) Reuters Limited 1997. </p></text>
<copyright>(c) 1997 Reuters Limited</copyright>
<metadata>
<codes class="bip:countries:1.0">
<code code="DEN">
<editdetail action="confirmed" attribution="Reuters BIP Coding Group" date="1997-01-03"></editdetail></code>
<code code="EURZ">
<editdetail action="confirmed" attribution="Reuters BIP Coding Group" date="1997-01-03"></editdetail></code>
<code code="SCANDZ">
<editdetail action="confirmed" attribution="Reuters BIP Coding Group" date="1997-01-03"></editdetail></code>
<code code="WEURZ">
<editdetail action="confirmed" attribution="Reuters BIP Coding Group" date="1997-01-03"></editdetail></code></codes>
<codes class="bip:topics:1.0">
<code code="M11">
<editdetail action="confirmed" attribution="Reuters BIP Coding Group" date="1997-01-03"></editdetail></code>
<code code="MCAT">
<editdetail action="confirmed" attribution="Reuters BIP Coding Group" date="1997-01-03"></editdetail></code></codes>
<dc element="dc.publisher" value="Reuters Holdings Plc"></dc>
<dc element="dc.datepublished" value="1997-01-03"></dc>
<dc element="dc.source" value="Reuters - Nyheder på dansk"></dc>
<dc element="dc.creator.location" value=""></dc>
<dc element="dc.creator.location.country.name" value=""></dc></metadata></newsitem>