<?xml version="1.0" encoding="UTF-8"?>

<newsitem date="1997-01-10" id="root" itemid="78911" xml:lang="da">
<title></title>
<headline> FALDENDE ANTAL KONKURSER I DECEMBER - DS. </headline>
<byline></byline>
<dateline></dateline>
<text>
<p>     KØBENHAVN, 10 januar (Reuter) -  I december 1996 blev </p>
<p> der registreret 142 konkurs-erklæringer. I forhold til </p>
<p> december 1995 er det faktiske antal faldet 16 pct., </p>
<p> oplyser Danmarks Statistik fredag. </p>
<p>     Det tre-måneders glidende gennemsnit for konkurser </p>
<p> (sæsonkorrigeret) viser en stigning på 11 pct. i den </p>
<p> seneste tre-måneders periode fra september til november </p>
<p> 1996. </p>
<p>          dec 96   nov 96   dec 95 Kundgjorte konkurser i alt 142 126 169 Sæsonkorrigeret       133 119 162 Tre-mdr glid. gennemsnit     - 132 174 </p>
<p> (/slj). </p>
<p> (c) Reuters Limited 1997. </p></text>
<copyright>(c) 1997 Reuters Limited</copyright>
<metadata>
<codes class="bip:countries:1.0">
<code code="DEN">
<editdetail action="confirmed" attribution="Reuters BIP Coding Group" date="1997-01-10"></editdetail></code>
<code code="EURZ">
<editdetail action="confirmed" attribution="Reuters BIP Coding Group" date="1997-01-10"></editdetail></code>
<code code="SCANDZ">
<editdetail action="confirmed" attribution="Reuters BIP Coding Group" date="1997-01-10"></editdetail></code>
<code code="WEURZ">
<editdetail action="confirmed" attribution="Reuters BIP Coding Group" date="1997-01-10"></editdetail></code></codes>
<codes class="bip:topics:1.0">
<code code="C16">
<editdetail action="confirmed" attribution="Reuters BIP Coding Group" date="1997-01-10"></editdetail></code>
<code code="CCAT">
<editdetail action="confirmed" attribution="Reuters BIP Coding Group" date="1997-01-10"></editdetail></code>
<code code="E11">
<editdetail action="confirmed" attribution="Reuters BIP Coding Group" date="1997-01-10"></editdetail></code>
<code code="ECAT">
<editdetail action="confirmed" attribution="Reuters BIP Coding Group" date="1997-01-10"></editdetail></code></codes>
<dc element="dc.publisher" value="Reuters Holdings Plc"></dc>
<dc element="dc.datepublished" value="1997-01-10"></dc>
<dc element="dc.source" value="Reuters - Nyheder på dansk"></dc>
<dc element="dc.creator.location" value=""></dc>
<dc element="dc.creator.location.country.name" value=""></dc></metadata></newsitem>