<?xml version="1.0" encoding="UTF-8"?>

<newsitem date="1997-02-14" id="root" itemid="80232" xml:lang="da">
<title></title>
<headline> EAC og T&amp;E enige om salg af skibe. </headline>
<byline></byline>
<dateline></dateline>
<text>
<p> KØBENHAVN, 14 februar (Reuter) - EAC og Tschudi &amp; Eitzen Holding (T&amp;E) har i dag underskrevet den endelige aftale, der dækker overtagelse af operatørvirksomheden EAC Shipping til T&amp;E. Det oplyser EAC i en pressemeddelelse fredag. </p>
<p> - Den regnskabsmæssige effekt af denne transaktion er for EAC i 1997 en omsætningsreduktion på omkring en halv milliard kroner og en reduktion i leasingforpligtelser på 190 mio. kr., skriver EAC. </p>
<p> Kontrakten omfatter de tre handymax tørlastskibe m.s. Cedrela, m.s. Canela samt m.s. Falstria. </p>
<p> Hensigtserklæringen med T&amp;E indeholdt også et tilbud til det børsnoterede Tschudi &amp; Eitzen Shipping om at overtage EAC&apos;s tankskibsoperatør-virksomhed samt ejerskab af den første og halvdelen af den tredie af de tre 30.000 tdw produkttankskibe, der - i samarbejde med D/S Norden - er under bygning i Ukraine. </p>
<p> - T&amp;E Shipping har besluttet ikke at udnytte denne option og i samråd med D/S Norden vil disse skibe nu blive tilbudt til anden side, hedder det videre. </p>
<p> Efter gennemførelsen af aftalen vil EAC&apos;s bogførte kapitalbinding i skibe, inklusive byggerater m.v for skibene i Ukraine, beløbe sig til knap 400 mio. kr. </p>
<p> Dette beløb kan stige til 500 mio. kr., hvis EAC mod forventning, skal modtage skibene, før de kan sælges videre. </p>
<p> Efter salget af skibene vil EAC&apos;s bogførte skibsaktiver forventeligt udgøre godt 250 mio. kr. </p>
<p> - Det forventes, at de tilbageværende skibsaktiviteters indflydelse på EAC-koncernens indtjening i 1997 vil være insignifikant, og fortsætter det fornuftige rateniveau, vil følsomheden for afhændelsestidspunktet for skibene være lille, skriver direktionen i EAC. </p>
<p> EAC venter, at opnå en mindre regnskabsmæssige avance ved det planlagte salg af aktiviteter og skibe, fremgår det. </p>
<p> - Jørn Nurkka (+45) 33 96 96 55. </p>
<p> (c) Reuters Limited 1997. </p></text>
<copyright>(c) 1997 Reuters Limited</copyright>
<metadata>
<codes class="bip:countries:1.0">
<code code="DEN">
<editdetail action="confirmed" attribution="Reuters BIP Coding Group" date="1997-02-14"></editdetail></code>
<code code="EURZ">
<editdetail action="confirmed" attribution="Reuters BIP Coding Group" date="1997-02-14"></editdetail></code>
<code code="NORW">
<editdetail action="confirmed" attribution="Reuters BIP Coding Group" date="1997-02-14"></editdetail></code>
<code code="SCANDZ">
<editdetail action="confirmed" attribution="Reuters BIP Coding Group" date="1997-02-14"></editdetail></code>
<code code="WEURZ">
<editdetail action="confirmed" attribution="Reuters BIP Coding Group" date="1997-02-14"></editdetail></code></codes>
<codes class="bip:topics:1.0">
<code code="DOK">
<editdetail action="confirmed" attribution="Reuters BIP Coding Group" date="1997-02-14"></editdetail></code>
<code code="ORNTDK">
<editdetail action="confirmed" attribution="Reuters BIP Coding Group" date="1997-02-14"></editdetail></code>
<code code="WIPRON">
<editdetail action="confirmed" attribution="Reuters BIP Coding Group" date="1997-02-14"></editdetail></code>
<code code="I61">
<editdetail action="confirmed" attribution="Reuters BIP Coding Group" date="1997-02-14"></editdetail></code>
<code code="I64">
<editdetail action="confirmed" attribution="Reuters BIP Coding Group" date="1997-02-14"></editdetail></code>
<code code="I74">
<editdetail action="confirmed" attribution="Reuters BIP Coding Group" date="1997-02-14"></editdetail></code>
<code code="ITSP">
<editdetail action="confirmed" attribution="Reuters BIP Coding Group" date="1997-02-14"></editdetail></code>
<code code="C15">
<editdetail action="confirmed" attribution="Reuters BIP Coding Group" date="1997-02-14"></editdetail></code>
<code code="C152">
<editdetail action="confirmed" attribution="Reuters BIP Coding Group" date="1997-02-14"></editdetail></code>
<code code="CCAT">
<editdetail action="confirmed" attribution="Reuters BIP Coding Group" date="1997-02-14"></editdetail></code></codes>
<dc element="dc.publisher" value="Reuters Holdings Plc"></dc>
<dc element="dc.datepublished" value="1997-02-14"></dc>
<dc element="dc.source" value="Reuters - Nyheder på dansk"></dc>
<dc element="dc.creator.location" value=""></dc>
<dc element="dc.creator.location.country.name" value=""></dc></metadata></newsitem>