<?xml version="1.0" encoding="UTF-8"?>

<newsitem date="1997-02-20" id="root" itemid="80458" xml:lang="da">
<title></title>
<headline> DEN DANSKE BANK 1996 EKSTRAORD UDGIFTER 754 MIO KR. </headline>
<byline></byline>
<dateline></dateline>
<text>
<p> KØBENHAVN, 20 februar (Reuter) - Den Danske Bank havde i 1996 ekstraordinære udgifter på i alt 756 mio. kr. mod 946 mio. kr. i 1995. Det fremgår af en regnskabsmeddelelse torsdag. </p>
<p> - Udgifterne i 1996 vedrører især pensionsforpligtelser, hensættelser i forbindelse med personalereduktionen, nedskrivninger af ejendomme samt yderligere hensættelse til investeringer i informationsteknologi, skriver banken. </p>
<p> Den Danske Bank fik i et resultat efter skat på 3.653 mio. kr. mod 3.631 mio. kr. i 1995. </p>
<p> (c) Reuters Limited 1997. </p></text>
<copyright>(c) 1997 Reuters Limited</copyright>
<metadata>
<codes class="bip:countries:1.0">
<code code="DEN">
<editdetail action="confirmed" attribution="Reuters BIP Coding Group" date="1997-02-20"></editdetail></code>
<code code="EURZ">
<editdetail action="confirmed" attribution="Reuters BIP Coding Group" date="1997-02-20"></editdetail></code>
<code code="SCANDZ">
<editdetail action="confirmed" attribution="Reuters BIP Coding Group" date="1997-02-20"></editdetail></code>
<code code="WEURZ">
<editdetail action="confirmed" attribution="Reuters BIP Coding Group" date="1997-02-20"></editdetail></code></codes>
<codes class="bip:topics:1.0">
<code code="DDB">
<editdetail action="confirmed" attribution="Reuters BIP Coding Group" date="1997-02-20"></editdetail></code>
<code code="I814">
<editdetail action="confirmed" attribution="Reuters BIP Coding Group" date="1997-02-20"></editdetail></code>
<code code="I81402">
<editdetail action="confirmed" attribution="Reuters BIP Coding Group" date="1997-02-20"></editdetail></code>
<code code="IBNK">
<editdetail action="confirmed" attribution="Reuters BIP Coding Group" date="1997-02-20"></editdetail></code>
<code code="C15">
<editdetail action="confirmed" attribution="Reuters BIP Coding Group" date="1997-02-20"></editdetail></code>
<code code="C151">
<editdetail action="confirmed" attribution="Reuters BIP Coding Group" date="1997-02-20"></editdetail></code>
<code code="C1511">
<editdetail action="confirmed" attribution="Reuters BIP Coding Group" date="1997-02-20"></editdetail></code>
<code code="CCAT">
<editdetail action="confirmed" attribution="Reuters BIP Coding Group" date="1997-02-20"></editdetail></code></codes>
<dc element="dc.publisher" value="Reuters Holdings Plc"></dc>
<dc element="dc.datepublished" value="1997-02-20"></dc>
<dc element="dc.source" value="Reuters - Nyheder på dansk"></dc>
<dc element="dc.creator.location" value=""></dc>
<dc element="dc.creator.location.country.name" value=""></dc></metadata></newsitem>