<?xml version="1.0" encoding="UTF-8"?>

<newsitem date="1997-03-12" id="root" itemid="81375" xml:lang="da">
<title></title>
<headline> Manglende købere trækker Novo-aktien ned - dealer. </headline>
<byline></byline>
<dateline></dateline>
<text>
<p> KØBENHAVN, 12 marts (Reuter) - Novo Nordisks aktie kan ikke fastholde den umiddelbare stigning, som kom efter offentliggørelsen af koncernens 1996-regnskab. Kursen på aktien ligger ved 14.40-tiden i 683 - et fald på 12 kr. i forhold til tirsdagens lukkekurs. Umiddelbart efter offentliggørelsen af regnskabet, der viste et resultat før skat på 2.521 mio. kr. mod 2.156 mio. kr. året før, steg aktien til kurs 704 fra kurs 686. </p>
<p> - Der var nogen som forsøgte, at handle aktien op lige efter offentliggørelsen af regnskabet, men de måtte hurtigt indse, at der ingen købere var på det niveau, siger en handler. </p>
<p> Handleren vurderer, at aktien på det nuværende kursniveau er for dyr, og at den nok skal længere ned i kurs. </p>
<p> - Markedet syntes, at aktien er ved at være godt betalt, og så ser man det klasssiske billede, at når regnskabet kommer, og er som forventet - så falder aktien. Det er en meget høj pris for Novo-aktien og aktien kan godt falde yderligere til et niveau omkring de 680, siger han. </p>
<p> Novo Nordisk sluttede tirsdag i kurs 695. </p>
<p> - Jørn Nurkka (+45) 33 96 96 55. </p>
<p> (c) Reuters Limited 1997. </p></text>
<copyright>(c) 1997 Reuters Limited</copyright>
<metadata>
<codes class="bip:countries:1.0">
<code code="DEN">
<editdetail action="confirmed" attribution="Reuters BIP Coding Group" date="1997-03-12"></editdetail></code>
<code code="EURZ">
<editdetail action="confirmed" attribution="Reuters BIP Coding Group" date="1997-03-12"></editdetail></code>
<code code="SCANDZ">
<editdetail action="confirmed" attribution="Reuters BIP Coding Group" date="1997-03-12"></editdetail></code>
<code code="WEURZ">
<editdetail action="confirmed" attribution="Reuters BIP Coding Group" date="1997-03-12"></editdetail></code></codes>
<codes class="bip:topics:1.0">
<code code="NOVO">
<editdetail action="confirmed" attribution="Reuters BIP Coding Group" date="1997-03-12"></editdetail></code>
<code code="I25">
<editdetail action="confirmed" attribution="Reuters BIP Coding Group" date="1997-03-12"></editdetail></code>
<code code="I257">
<editdetail action="confirmed" attribution="Reuters BIP Coding Group" date="1997-03-12"></editdetail></code>
<code code="C15">
<editdetail action="confirmed" attribution="Reuters BIP Coding Group" date="1997-03-12"></editdetail></code>
<code code="C152">
<editdetail action="confirmed" attribution="Reuters BIP Coding Group" date="1997-03-12"></editdetail></code>
<code code="C18">
<editdetail action="confirmed" attribution="Reuters BIP Coding Group" date="1997-03-12"></editdetail></code>
<code code="C181">
<editdetail action="confirmed" attribution="Reuters BIP Coding Group" date="1997-03-12"></editdetail></code>
<code code="CCAT">
<editdetail action="confirmed" attribution="Reuters BIP Coding Group" date="1997-03-12"></editdetail></code></codes>
<dc element="dc.publisher" value="Reuters Holdings Plc"></dc>
<dc element="dc.datepublished" value="1997-03-12"></dc>
<dc element="dc.source" value="Reuters - Nyheder på dansk"></dc>
<dc element="dc.creator.location" value=""></dc>
<dc element="dc.creator.location.country.name" value=""></dc></metadata></newsitem>