<?xml version="1.0" encoding="UTF-8"?>

<newsitem date="1997-06-30" id="root" itemid="85237" xml:lang="da">
<title></title>
<headline> DAGSKALENDER - Reuters Finans mandag 30 juni. </headline>
<byline></byline>
<dateline></dateline>
<text>
<p> Her følger et udsnit af de begivenheder, der ventes at få indflydelse på de danske finansmarkeder i dag: </p>
<p> * DANMARKS STATISTIK KL. 9.30: </p>
<p> - BNP 1. kvartal 1997. Ni økonomer venter i gennemsnit en BNP-vækst på 3,4 pct. år/år efter en vækst i 4 kvt. 1996 på 3,3 pct. år/år. </p>
<p> * FONDSBØRSEN: </p>
<p> - Sidste handelsdag for delbeviser i Søndagsavisen </p>
<p> - Danske Invest Fjernøsten noteres </p>
<p> - 4 pct. Nord/LB 1997/1999 noteres </p>
<p> * USA: </p>
<p> - Personlig indkomst og forbrug maj (1430). Et Reuters konsensus tyder på en stigning i både indkomst og forbrug på 0,3 pct. </p>
<p> - Nybolig salg juni. (1600) </p>
<p> * FRANKRIG: </p>
<p> - Ledighed maj (0845). Der ventes en uændret ledighed på 12,8 pct. </p>
<p> * I LØBET AF UGEN: </p>
<p> - Regnskaber: </p>
<p> - GN Store Nord Holding </p>
<p> * Tyskland: </p>
<p> - Industriproduktion maj (tors-man). Et Reuters konsensus tyder på en årsstigningstakt på 2,3 pct. </p>
<p> * Helligdage: </p>
<p> - USA fredag (uafhængighedsdag) </p>
<p> Indeks til kalendere for forskellige markeder og lande fås ved at dobbeltklikke her: [IND/DIARY] </p>
<p> Reuters Finans: Tlf.: 33 96 96 58. Fax: 33 93 84 57. </p>
<p> (c) Reuters Limited 1997. </p></text>
<copyright>(c) 1997 Reuters Limited</copyright>
<metadata>
<codes class="bip:countries:1.0">
<code code="DEN">
<editdetail action="confirmed" attribution="Reuters BIP Coding Group" date="1997-06-30"></editdetail></code>
<code code="EURZ">
<editdetail action="confirmed" attribution="Reuters BIP Coding Group" date="1997-06-30"></editdetail></code>
<code code="SCANDZ">
<editdetail action="confirmed" attribution="Reuters BIP Coding Group" date="1997-06-30"></editdetail></code>
<code code="WEURZ">
<editdetail action="confirmed" attribution="Reuters BIP Coding Group" date="1997-06-30"></editdetail></code></codes>
<codes class="bip:topics:1.0">
<code code="CCAT">
<editdetail action="confirmed" attribution="Reuters BIP Coding Group" date="1997-06-30"></editdetail></code>
<code code="ECAT">
<editdetail action="confirmed" attribution="Reuters BIP Coding Group" date="1997-06-30"></editdetail></code>
<code code="GCAT">
<editdetail action="confirmed" attribution="Reuters BIP Coding Group" date="1997-06-30"></editdetail></code>
<code code="MCAT">
<editdetail action="confirmed" attribution="Reuters BIP Coding Group" date="1997-06-30"></editdetail></code></codes>
<dc element="dc.publisher" value="Reuters Holdings Plc"></dc>
<dc element="dc.datepublished" value="1997-06-30"></dc>
<dc element="dc.source" value="Reuters - Nyheder på dansk"></dc>
<dc element="dc.creator.location" value=""></dc>
<dc element="dc.creator.location.country.name" value=""></dc></metadata></newsitem>